README.rst
setup.py
django_galicia/__init__.py
django_galicia/comarcas.py
django_galicia/forms.py
django_galicia/municipalities.py
django_galicia/provinces.py
django_galicia.egg-info/PKG-INFO
django_galicia.egg-info/SOURCES.txt
django_galicia.egg-info/dependency_links.txt
django_galicia.egg-info/top_level.txt