Metadata-Version: 1.1
Name: django-galicia
Version: 0.11
Summary: Django helpers for Galicia (Spain).
Home-page: https://bitbucket.org/fonso/django-galicia
Author: Afonso Fernandez Nogueira
Author-email: fonzzo+django-galicia@gmail.com
License: BSD
Platform: UNKNOWN
Classifier: Development Status :: 1 - Planning
Classifier: Environment :: Web Environment
Classifier: Framework :: Django
Classifier: Intended Audience :: Developers
Classifier: License :: OSI Approved :: BSD License
Classifier: Operating System :: OS Independent
Classifier: Programming Language :: Python
